yachalk/__init__.py
yachalk/ansi.py
yachalk/chalk_builder.py
yachalk/chalk_factory.py
yachalk/chalk_instance.py
yachalk/py.typed
yachalk/supports_color.py
yachalk/types.py
yachalk/utils.py
yachalk-0.1.8.dist-info/LICENSE
yachalk-0.1.8.dist-info/METADATA
yachalk-0.1.8.dist-info/WHEEL
yachalk-0.1.8.dist-info/top_level.txt
yachalk-0.1.8.dist-info/RECORD
