Metadata-Version: 2.1
Name: yachalk
Version: 0.1.8
Summary: 🖍️ Terminal string styling done right
Home-page: https://github.com/bluenote10/yachalk
License: MIT
Keywords: terminal,color,styling,ansi
Classifier: Intended Audience :: Developers
Classifier: License :: OSI Approved :: MIT License
Classifier: Operating System :: OS Independent
Classifier: Programming Language :: Python :: 3
Classifier: Topic :: Terminals
Classifier: Topic :: System :: Logging
License-File: LICENSE
Requires-Dist: setuptools
Requires-Dist: importlib-resources
